parser_binding/__init__.py
parser_binding/parser.py
parser_binding/types.py
parser_binding/utils.py
parser_binding/tests/__init__.py
parser_binding/tests/test_parser.py
parser_binding/tests/test_training_args.py
parser_binding/tests/test_utils.py
parser_binding-0.1.2.dist-info/LICENSE
parser_binding-0.1.2.dist-info/METADATA
parser_binding-0.1.2.dist-info/WHEEL
parser_binding-0.1.2.dist-info/top_level.txt
parser_binding-0.1.2.dist-info/RECORD
