Metadata-Version: 2.1
Name: parser-binding
Version: 0.1.2
Summary: The parser to bind the dataclasses conviniently.
Home-page: https://github.com/zipzou/parser-binding
Author: zipzou
License: MIT
Classifier: Programming Language :: Python
Classifier: Programming Language :: Python :: 3
Classifier: Programming Language :: Python :: 3.7
Classifier: Programming Language :: Python :: 3.8
Classifier: Programming Language :: Python :: 3.9
Classifier: Programming Language :: Python :: 3.10
Classifier: Programming Language :: Python :: 3.11
Requires-Python: >=3.7
License-File: LICENSE
